vezor-1.0.1.dist-info/licenses/LICENSE
zar/__init__.py
zar/help.py
zar/print.py
zar/write.py
zar/formula/__init__.py
zar/formula/min_distance.py
zar/formula/prime_list.py
zar/formula/gcd/__init__.py
zar/formula/gcd/gcd.py
zar/formula/gcd/gcd2.py
zar/formula/gcd/gcd3.py
zar/formula/gcd/gcd4.py
zar/geometry/__init__.py
zar/geometry/circle.py
zar/searching/__init__.py
zar/searching/binary_search.py
zar/searching/linear_search.py
zar/searching/ordered_linear_search.py
zar/searching/unordered_linear_search.py
zar/sorting/__init__.py
zar/sorting/bubble_sort.py
zar/sorting/comparison_counting_sort.py
zar/sorting/counting_sort.py
zar/sorting/cycle_sort.py
zar/sorting/heap_sort.py
zar/sorting/insertion_sort.py
zar/sorting/merge_sort.py
zar/sorting/quick_sort.py
zar/sorting/radix_sort.py
zar/sorting/three_way_merge_sort.py
vezor-1.0.1.dist-info/METADATA
vezor-1.0.1.dist-info/WHEEL
vezor-1.0.1.dist-info/top_level.txt
vezor-1.0.1.dist-info/RECORD
