Metadata-Version: 2.4
Name: vezor
Version: 1.0.1
Summary: A collection of algorithm designs for easy application to assist mathematical problems.
Home-page: https://github.com/avezoor/vezor
Author: Izzar Suly Nashrudin
Author-email: Izzarsuly@proton.me
Classifier: Programming Language :: Python :: 3
Classifier: License :: OSI Approved :: MIT License
Classifier: Operating System :: OS Independent
Classifier: Operating System :: Microsoft :: Windows
Classifier: Operating System :: MacOS :: MacOS X
Classifier: Operating System :: POSIX :: Linux
Classifier: Operating System :: Unix
Classifier: Framework :: Jupyter
Requires-Python: >=3.6
License-File: LICENSE
Dynamic: author
Dynamic: author-email
Dynamic: classifier
Dynamic: description
Dynamic: description-content-type
Dynamic: home-page
Dynamic: license-file
Dynamic: requires-python
Dynamic: summary
